ls/__init__.py
ls/joyful/__init__.py
ls/joyful/_version.py
ls/joyful/admin.py
ls/joyful/apps.py
ls/joyful/models.py
ls/joyful/tests.py
ls/joyful/utils.py
ls/joyful/views.py
ls/joyful/locale/fr/LC_MESSAGES/django.mo
ls/joyful/locale/fr/LC_MESSAGES/django.po
ls/joyful/migrations/0001_initial.py
ls/joyful/migrations/0002_auto_20200817_1712.py
ls/joyful/migrations/__init__.py
ls/joyful/static/joyful/css/joyful.css
ls/joyful/static/joyful/css/vendor/fullcalendar-5.2.0.min.css
ls/joyful/static/joyful/img/logo.png
ls/joyful/static/joyful/js/vendor/fullcalendar-5.2.0.min.js
ls/joyful/templates/joyful/full_calendar_page.html
ls.joyful-0.1.3.dist-info/LICENSE
ls.joyful-0.1.3.dist-info/METADATA
ls.joyful-0.1.3.dist-info/WHEEL
ls.joyful-0.1.3.dist-info/top_level.txt
ls.joyful-0.1.3.dist-info/RECORD
