Metadata-Version: 2.1
Name: ls.joyful
Version: 0.1.3
Summary: A FullCalendar front end to Joyous.
Home-page: https://github.com/linuxsoftware/ls.joyful
Author: David Moore
Author-email: david@linuxsoftware.co.nz
License: BSD
Keywords: calendar,wagtail,fullcalendar,joyous,joyful
Platform: any
Classifier: Development Status :: 4 - Beta
Classifier: Framework :: Django
Classifier: Framework :: Wagtail
Classifier: Framework :: Wagtail :: 2
Classifier: License :: OSI Approved :: BSD License
Classifier: Operating System :: OS Independent
Classifier: Programming Language :: Python
Classifier: Programming Language :: Python :: 3
Classifier: Topic :: Office/Business :: Groupware
Classifier: Topic :: Office/Business :: Scheduling
Classifier: Topic :: Software Development :: Libraries :: Python Modules
Requires-Dist: ls.joyous (>=1.0)
Requires-Dist: wagtail (>=2.0)
